mcp_bauplan/__init__.py
mcp_bauplan/main.py
mcp_bauplan/mcp_config.py
mcp_bauplan/server.py
mcp_bauplan-0.9.1.dist-info/METADATA
mcp_bauplan-0.9.1.dist-info/WHEEL
mcp_bauplan-0.9.1.dist-info/entry_points.txt
mcp_bauplan-0.9.1.dist-info/licenses/LICENSE
mcp_bauplan-0.9.1.dist-info/RECORD
